LICENSE
README.rst
pyproject.toml
src/latexmk/__init__.py
src/latexmk/__main__.py
src/latexmk.egg-info/PKG-INFO
src/latexmk.egg-info/SOURCES.txt
src/latexmk.egg-info/dependency_links.txt
src/latexmk.egg-info/top_level.txt