Metadata-Version: 2.4
Name: latexmk
Version: 0.0.1
Summary: Tool for building a latex project
Author: Jacob Striebel
License-Expression: MIT
Project-URL: Homepage, https://github.com/striebel/latexmk
Classifier: Programming Language :: Python :: 3
Classifier: Operating System :: POSIX :: Linux
Requires-Python: >=3.8
License-File: LICENSE
Dynamic: license-file
